{
  "platos": [
    {
      "calorias": 400,
      "descripcion": "con ensalada",
      "id": 7668,
      "inOffer": true,
      "oferta": 0.02,
      "precioPlato": 250,
      "titulo": "Tat煤 a la parrilla"
    },
    {
      "calorias": 80,
      "descripcion": "sin nada, bien econ贸mico",
      "id": 1,
      "inOffer": false,
      "oferta": 0,
      "precioPlato": 6464,
      "titulo": "nombre"
    },
    {
      "calorias": 91,
      "descripcion": "descripci贸n del plato creado con holder",
      "id": 2,
      "inOffer": false,
      "oferta": 0,
      "precioPlato": 35,
      "titulo": "plato creado con Holder"
    },
    {
      "calorias": 120,
      "descripcion": "el m谩s ordinario",
      "id": 7670,
      "inOffer": true,
      "oferta": 0.5,
      "precioPlato": 65,
      "titulo": "Sanguche de salamin"
    },
    {
      "calorias": 250,
      "descripcion": "con todo lo que qued贸 del d铆a anterior",
      "inOffer": false,
      "oferta": 0,
      "precioPlato": 60,
      "titulo": "tarta de sobra",
      "id": 7671
    },
    {
      "calorias": 840,
      "descripcion": "jgg",
      "inOffer": false,
      "oferta": 0,
      "precioPlato": 2438,
      "titulo": "morcilla negra XXL",
      "id": 7672
    },
    {
      "calorias": 80,
      "descripcion": "buen barato",
      "inOffer": false,
      "oferta": 0,
      "precioPlato": 50,
      "titulo": "Picadillo con galletitas",
      "id": 7673
    },
    {
      "calorias": 0,
      "descripcion": "eso man",
      "inOffer": false,
      "oferta": 0,
      "precioPlato": 350,
      "titulo": "Vaso de awa",
      "id": 7674
    },
    {
      "calorias": 500,
      "descripcion": "ordinario como canap茅 de mortadela",
      "inOffer": false,
      "oferta": 0,
      "precioPlato": 250,
      "titulo": "Chorizo de caballo con papas bravas",
      "id": 7675
    },
    {
      "calorias": 25,
      "descripcion": "para 100 personas",
      "id": 7676,
      "inOffer": false,
      "oferta": 0,
      "precioPlato": 25000,
      "titulo": "Picada \"El gobernador\""
    },
    {
      "calorias": 0,
      "descripcion": "esto no es mercado libre eh?",
      "inOffer": false,
      "oferta": 0,
      "precioPlato": 1200,
      "titulo": "Carburador de duna usado",
      "id": 7677
    },
    {
      "calorias": 200,
      "descripcion": "no seas trolo Man",
      "inOffer": false,
      "oferta": 0,
      "precioPlato": 450,
      "titulo": "Hamburguesa vegana",
      "id": 7678
    },
    {
      "calorias": 29,
      "descripcion": "una empanada, pero de carne",
      "inOffer": false,
      "oferta": 0,
      "precioPlato": 30,
      "titulo": "empanada de carne",
      "id": 7679
    },
    {
      "calorias": 0,
      "descripcion": "agua de calidad premium para su paladar",
      "inOffer": false,
      "oferta": 0,
      "precioPlato": 10,
      "titulo": "awa caliente pal mate",
      "id": 7680
    },
    {
      "calorias": 50,
      "descripcion": "m谩s duro que el maestruli",
      "inOffer": false,
      "oferta": 0,
      "precioPlato": 20,
      "titulo": "guebo duro",
      "id": 7681
    },
    {
      "calorias": 500,
      "descripcion": "un kilo",
      "inOffer": false,
      "oferta": 0,
      "precioPlato": 250,
      "titulo": "helado crema del cielo",
      "id": 7682
    },
    {
      "calorias": 20,
      "descripcion": "esa que estaba en la heladera",
      "id": 7683,
      "inOffer": false,
      "oferta": 0,
      "precioPlato": 0,
      "titulo": "manzana del anexo"
    },
    {
      "calorias": 60,
      "descripcion": "especial para los viernes de balc贸n",
      "inOffer": false,
      "oferta": 0,
      "precioPlato": 80,
      "titulo": "Porr贸n de litro",
      "id": 7684
    },
    {
      "calorias": 250,
      "descripcion": "re cool pa caretiar",
      "inOffer": false,
      "oferta": 0,
      "precioPlato": 180,
      "titulo": "sushi de moncholo",
      "id": 7685
    },
    {
      "calorias": 68,
      "descripcion": "la de la serie esa que son todos amarillos",
      "inOffer": false,
      "oferta": 0,
      "precioPlato": 250,
      "titulo": "crosti burguer",
      "id": 7686
    },
    {
      "calorias": 580,
      "descripcion": "la del dibujito ese",
      "inOffer": false,
      "oferta": 0,
      "precioPlato": 249.99,
      "titulo": "cangreburguer",
      "id": 7687
    }
  ],
  "pedidos": [
    {
      "estado": "ENVIADO",
      "fecha": "Nov 5, 2019 8:25:15 PM",
      "id": 397664392,
      "itemsPedido": [
        {
          "cantidad": 1,
          "id": 1,
          "idPedido": 397664392,
          "plato": {
            "calorias": 91,
            "descripcion": "descripci贸n del plato creado con holder",
            "id": 2,
            "inOffer": false,
            "oferta": 0,
            "precioPlato": 35,
            "titulo": "plato creado con Holder"
          },
          "precioItem": 35
        },
        {
          "cantidad": 2,
          "id": 2,
          "idPedido": 397664392,
          "plato": {
            "calorias": 250,
            "descripcion": "con todo lo que qued贸 del d铆a anterior",
            "id": 7671,
            "inOffer": false,
            "oferta": 0,
            "precioPlato": 60,
            "titulo": "tarta de sobra"
          },
          "precioItem": 120
        },
        {
          "cantidad": 1,
          "id": 3,
          "idPedido": 397664392,
          "plato": {
            "calorias": 400,
            "descripcion": "con ensalada",
            "id": 7668,
            "inOffer": true,
            "oferta": 0.02,
            "precioPlato": 250,
            "titulo": "Tat煤 a la parrilla"
          },
          "precioItem": 245
        }
      ],
      "latitud": -31.620743617533957,
      "longitud": -60.67867744714021
    },
    {
      "estado": "ENVIADO",
      "fecha": "Nov 5, 2019 8:25:41 PM",
      "id": 1113571017,
      "itemsPedido": [
        {
          "cantidad": 5,
          "id": 4,
          "idPedido": 1113571017,
          "plato": {
            "calorias": 91,
            "descripcion": "descripci贸n del plato creado con holder",
            "id": 2,
            "inOffer": false,
            "oferta": 0,
            "precioPlato": 35,
            "titulo": "plato creado con Holder"
          },
          "precioItem": 175
        }
      ],
      "latitud": -31.605666278924602,
      "longitud": -60.691593289375305
    },
    {
      "estado": "ENVIADO",
      "fecha": "Nov 5, 2019 8:26:02 PM",
      "id": 1758214259,
      "itemsPedido": [
        {
          "cantidad": 15,
          "id": 5,
          "idPedido": 1758214259,
          "plato": {
            "calorias": 25,
            "descripcion": "para 100 personas",
            "id": 7676,
            "inOffer": false,
            "oferta": 0,
            "precioPlato": 25000,
            "titulo": "Picada \"El gobernador\""
          },
          "precioItem": 375000
        }
      ],
      "latitud": -31.657924284330203,
      "longitud": -60.710476376116276
    },
    {
      "estado": "ENVIADO",
      "fecha": "Nov 5, 2019 8:37:43 PM",
      "id": 370550295,
      "itemsPedido": [
        {
          "cantidad": 3,
          "id": 7,
          "idPedido": 370550295,
          "plato": {
            "calorias": 400,
            "descripcion": "con ensalada",
            "id": 7668,
            "inOffer": true,
            "oferta": 0.02,
            "precioPlato": 250,
            "titulo": "Tat煤 a la parrilla"
          },
          "precioItem": 735
        }
      ],
      "latitud": -31.606911252610267,
      "longitud": -60.68500947207213
    },
    {
      "estado": "ENVIADO",
      "fecha": "Nov 5, 2019 8:38:09 PM",
      "id": -888781352,
      "itemsPedido": [
        {
          "cantidad": 2,
          "id": 8,
          "idPedido": -888781352,
          "plato": {
            "calorias": 0,
            "descripcion": "eso man",
            "id": 7674,
            "inOffer": false,
            "oferta": 0,
            "precioPlato": 350,
            "titulo": "Vaso de awa"
          },
          "precioItem": 700
        }
      ],
      "latitud": -31.61037424781978,
      "longitud": -60.68560894578695
    },
    {
      "estado": "ENVIADO",
      "fecha": "Nov 5, 2019 8:39:48 PM",
      "id": -1856883705,
      "itemsPedido": [
        {
          "cantidad": 11,
          "id": 9,
          "idPedido": -1856883705,
          "plato": {
            "calorias": 91,
            "descripcion": "descripci贸n del plato creado con holder",
            "id": 2,
            "inOffer": false,
            "oferta": 0,
            "precioPlato": 35,
            "titulo": "plato creado con Holder"
          },
          "precioItem": 385
        },
        {
          "cantidad": 2,
          "id": 10,
          "idPedido": -1856883705,
          "plato": {
            "calorias": 400,
            "descripcion": "con ensalada",
            "id": 7668,
            "inOffer": true,
            "oferta": 0.02,
            "precioPlato": 250,
            "titulo": "Tat煤 a la parrilla"
          },
          "precioItem": 490
        }
      ],
      "latitud": -31.63574971928374,
      "longitud": -60.70266846567392
    },
    {
      "estado": "ENVIADO",
      "fecha": "Nov 5, 2019 8:41:23 PM",
      "id": -1225254952,
      "itemsPedido": [
        {
          "cantidad": 12,
          "id": 11,
          "idPedido": -1225254952,
          "plato": {
            "calorias": 29,
            "descripcion": "una empanada, pero de carne",
            "id": 7679,
            "inOffer": false,
            "oferta": 0,
            "precioPlato": 30,
            "titulo": "empanada de carne"
          },
          "precioItem": 360
        },
        {
          "cantidad": 10,
          "id": 12,
          "idPedido": -1225254952,
          "plato": {
            "calorias": 400,
            "descripcion": "con ensalada",
            "id": 7668,
            "inOffer": true,
            "oferta": 0.02,
            "precioPlato": 250,
            "titulo": "Tat煤 a la parrilla"
          },
          "precioItem": 2450
        },
        {
          "cantidad": 2,
          "id": 13,
          "idPedido": -1225254952,
          "plato": {
            "calorias": 80,
            "descripcion": "sin nada, bien econ贸mico",
            "id": 1,
            "inOffer": false,
            "oferta": 0,
            "precioPlato": 6464,
            "titulo": "nombre"
          },
          "precioItem": 12928
        }
      ],
      "latitud": -31.62244318401914,
      "longitud": -60.70403572171926
    },
    {
      "estado": "ENVIADO",
      "fecha": "Nov 5, 2019 8:43:19 PM",
      "id": -1972937063,
      "itemsPedido": [
        {
          "cantidad": 13,
          "id": 14,
          "idPedido": -1972937063,
          "plato": {
            "calorias": 400,
            "descripcion": "con ensalada",
            "id": 7668,
            "inOffer": true,
            "oferta": 0.02,
            "precioPlato": 250,
            "titulo": "Tat煤 a la parrilla"
          },
          "precioItem": 3185
        }
      ],
      "latitud": -31.62625817376456,
      "longitud": -60.69975525140762
    },
    {
      "estado": "ENVIADO",
      "fecha": "Nov 5, 2019 8:44:48 PM",
      "id": -2121487273,
      "itemsPedido": [
        {
          "cantidad": 4,
          "id": 15,
          "idPedido": -2121487273,
          "plato": {
            "calorias": 80,
            "descripcion": "sin nada, bien econ贸mico",
            "id": 1,
            "inOffer": true,
            "oferta": 0.5,
            "precioPlato": 6464,
            "titulo": "nombre"
          },
          "precioItem": 12928
        }
      ],
      "latitud": -31.616000483753428,
      "longitud": -60.68557173013687
    },
    {
      "estado": "ENVIADO",
      "fecha": "Nov 5, 2019 8:55:20 PM",
      "id": -538269113,
      "itemsPedido": [
        {
          "cantidad": 1,
          "id": 16,
          "idPedido": -538269113,
          "plato": {
            "calorias": 400,
            "descripcion": "con ensalada",
            "id": 7668,
            "inOffer": true,
            "oferta": 0.02,
            "precioPlato": 250,
            "titulo": "Tat煤 a la parrilla"
          },
          "precioItem": 245
        }
      ],
      "latitud": -31.620182322674157,
      "longitud": -60.68840011954308
    },
    {
      "estado": "ENVIADO",
      "fecha": "Nov 5, 2019 9:09:26 PM",
      "id": 943998939,
      "itemsPedido": [
        {
          "cantidad": 1,
          "id": 17,
          "idPedido": 943998939,
          "plato": {
            "calorias": 80,
            "descripcion": "sin nada, bien econ贸mico",
            "id": 1,
            "inOffer": true,
            "oferta": 0.5,
            "precioPlato": 6464,
            "titulo": "nombre"
          },
          "precioItem": 3232
        }
      ],
      "latitud": -31.61240549954928,
      "longitud": -60.681537352502346
    },
    {
      "estado": "ENVIADO",
      "fecha": "Nov 6, 2019 1:53:16 PM",
      "id": -563397857,
      "itemsPedido": [
        {
          "cantidad": 1,
          "id": 18,
          "idPedido": -563397857,
          "plato": {
            "calorias": 400,
            "descripcion": "con ensalada",
            "id": 7668,
            "inOffer": true,
            "oferta": 0.02,
            "precioPlato": 250,
            "titulo": "Tat煤 a la parrilla"
          },
          "precioItem": 245
        },
        {
          "cantidad": 2,
          "id": 19,
          "idPedido": -563397857,
          "plato": {
            "calorias": 500,
            "descripcion": "un kilo",
            "id": 7682,
            "inOffer": false,
            "oferta": 0,
            "precioPlato": 250,
            "titulo": "helado crema del cielo"
          },
          "precioItem": 500
        }
      ],
      "latitud": -31.605938975272643,
      "longitud": -60.69124929606914
    }
  ]
}